patchmix/__init__.py
patchmix/mix.py
patchmix-0.1.dist-info/LICENSE
patchmix-0.1.dist-info/METADATA
patchmix-0.1.dist-info/WHEEL
patchmix-0.1.dist-info/top_level.txt
patchmix-0.1.dist-info/RECORD
