Metadata-Version: 2.1
Name: patchmix
Version: 0.1
Summary: This is the official implementation of paper: "Inter-Instance Similarity Modeling for Contrastive Learning".
Home-page: https://github.com/visresearch/patchmix
Author: DaWei Liu
Author-email: liudw0702@163.com
License: MIT
Keywords: Self-Supervise,Computer Vision,Mix Augmentation
Classifier: Development Status :: 3 - Alpha
Classifier: Intended Audience :: Developers
Classifier: Topic :: Software Development :: Build Tools
Classifier: License :: OSI Approved :: MIT License
Classifier: Programming Language :: Python :: 3.6
Classifier: Programming Language :: Python :: 3.7
Classifier: Programming Language :: Python :: 3.8
Classifier: Programming Language :: Python :: 3.9
License-File: LICENSE
Requires-Dist: torch
Requires-Dist: numpy
